odoo/addons/l10n_es_aeat_mod322/README.rst
odoo/addons/l10n_es_aeat_mod322/__init__.py
odoo/addons/l10n_es_aeat_mod322/__manifest__.py
odoo/addons/l10n_es_aeat_mod322/data/2023/aeat.model.export.config.csv
odoo/addons/l10n_es_aeat_mod322/data/2023/aeat.model.export.config.line.csv
odoo/addons/l10n_es_aeat_mod322/data/2023/l10n.es.aeat.map.tax.csv
odoo/addons/l10n_es_aeat_mod322/data/2023/l10n.es.aeat.map.tax.line.csv
odoo/addons/l10n_es_aeat_mod322/i18n/es.po
odoo/addons/l10n_es_aeat_mod322/i18n/l10n_es_aeat_mod322.pot
odoo/addons/l10n_es_aeat_mod322/models/__init__.py
odoo/addons/l10n_es_aeat_mod322/models/l10n_es_aeat_mod322_group.py
odoo/addons/l10n_es_aeat_mod322/models/l10n_es_aeat_mod322_report.py
odoo/addons/l10n_es_aeat_mod322/readme/CONTRIBUTORS.rst
odoo/addons/l10n_es_aeat_mod322/readme/DESCRIPTION.rst
odoo/addons/l10n_es_aeat_mod322/readme/USAGE.rst
odoo/addons/l10n_es_aeat_mod322/security/ir.model.access.csv
odoo/addons/l10n_es_aeat_mod322/security/security.xml
odoo/addons/l10n_es_aeat_mod322/static/description/icon.png
odoo/addons/l10n_es_aeat_mod322/static/description/icon_source.svg
odoo/addons/l10n_es_aeat_mod322/static/description/index.html
odoo/addons/l10n_es_aeat_mod322/tests/__init__.py
odoo/addons/l10n_es_aeat_mod322/tests/test_mod322.py
odoo/addons/l10n_es_aeat_mod322/views/l10n_es_aeat_mod322_group.xml
odoo/addons/l10n_es_aeat_mod322/views/l10n_es_aeat_mod322_report.xml
odoo14_addon_l10n_es_aeat_mod322-14.0.1.0.1.dist-info/METADATA
odoo14_addon_l10n_es_aeat_mod322-14.0.1.0.1.dist-info/WHEEL
odoo14_addon_l10n_es_aeat_mod322-14.0.1.0.1.dist-info/top_level.txt
odoo14_addon_l10n_es_aeat_mod322-14.0.1.0.1.dist-info/RECORD
